README.rst
setup.py
django_modelhint/__init__.py
django_modelhint/testing.py
django_modelhint.egg-info/PKG-INFO
django_modelhint.egg-info/SOURCES.txt
django_modelhint.egg-info/dependency_links.txt
django_modelhint.egg-info/entry_points.txt
django_modelhint.egg-info/not-zip-safe
django_modelhint.egg-info/requires.txt
django_modelhint.egg-info/top_level.txt
django_modelhint/tests/__init__.py
django_modelhint/tests/test_it.py