Metadata-Version: 1.1
Name: django-modelhint
Version: 0.1.1
Summary: add annotations at django models fields
Home-page: https://github.com/podhmo/django-modelhint
Author: UNKNOWN
Author-email: UNKNOWN
License: UNKNOWN
Platform: UNKNOWN
Classifier: Programming Language :: Python
Classifier: Programming Language :: Python :: Implementation :: CPython
